lilo/mdof/__init__.py
lilo.mdof-0.0.0.dist-info/METADATA
lilo.mdof-0.0.0.dist-info/WHEEL
lilo.mdof-0.0.0.dist-info/top_level.txt
lilo.mdof-0.0.0.dist-info/RECORD
